pytt_miniapp/__init__.py
pytt_miniapp/miniapp.py
pytt_miniapp-1.0.0.dist-info/METADATA
pytt_miniapp-1.0.0.dist-info/WHEEL
pytt_miniapp-1.0.0.dist-info/top_level.txt
pytt_miniapp-1.0.0.dist-info/RECORD
